Biden-1.0.1.dist-info/METADATA
Biden-1.0.1.dist-info/RECORD
Biden-1.0.1.dist-info/WHEEL
Biden-1.0.1.dist-info/top_level.txt
DbFactory/__init__.py
DbFactory/biden.py
