Metadata-Version: 2.1
Name: Biden
Version: 1.0.1
Summary: Hi Biden!
Home-page: UNKNOWN
Author: Caturbhuja
Author-email: caturbhuja@foxmail.com
License: MIT
Platform: UNKNOWN
